memory_efficient_transformer/__init__.py
memory_efficient_transformer/models/__init__.py
memory_efficient_transformer/models/attention.py
memory_efficient_transformer/models/transformer.py
memory_efficient_transformer/utils/__init__.py
memory_efficient_transformer/utils/jax/utils.py
memory_efficient_transformer/utils/stub/load_state_dict.py
memory_efficient_transformer_pytorch-0.2.0.dist-info/WHEEL
memory_efficient_transformer_pytorch-0.2.0.dist-info/METADATA
memory_efficient_transformer_pytorch-0.2.0.dist-info/RECORD
